bt/__init__.py
bt/behaviour_tree.py
bt/logger.py
py_bt-1.2.1.dist-info/LICENSE
py_bt-1.2.1.dist-info/METADATA
py_bt-1.2.1.dist-info/WHEEL
py_bt-1.2.1.dist-info/top_level.txt
py_bt-1.2.1.dist-info/zip-safe
py_bt-1.2.1.dist-info/RECORD
