Metadata-Version: 2.1
Name: py-bt
Version: 1.2.1
Summary: Python package for modelling and executing Behaviour Trees.
Home-page: https://github.com/dlavelle7/py-bt
Author: David Lavelle
Author-email: davidlavelle1@hotmail.com
License: UNKNOWN
Platform: UNKNOWN
Classifier: Programming Language :: Python :: 3
Classifier: License :: OSI Approved :: MIT License
Requires-Dist: PyYAML (==5.3)
Requires-Dist: jsonschema (==3.2.0)
